dral/__init__.py
dral/adapter/__init__.py
dral/adapter/base.py
dral/adapter/svd.py
dral/adapter/white_black_list.py
dral/app.py
dral/devices/__init__.py
dral/devices/arm/__init__.py
dral/devices/arm/example/__init__.py
dral/devices/arm/example/example1.svd
dral/devices/stm32/__init__.py
dral/devices/stm32/f4/__init__.py
dral/devices/stm32/f4/stm32f411.svd
dral/devices/stm32/f4/stm32f446.svd
dral/filter/__init__.py
dral/filter/banks.py
dral/filter/base.py
dral/filter/black_list.py
dral/filter/white_list.py
dral/format/__init__.py
dral/format/base.py
dral/format/cmake_lib.py
dral/format/mbedautomatify.py
dral/format/single_file.py
dral/generator.py
dral/objects.py
dral/templates/__init__.py
dral/templates/dral/__init__.py
dral/templates/dral/bank.dral
dral/templates/dral/bank.field.dral
dral/templates/dral/field.dral
dral/templates/dral/model.dral
dral/templates/dral/peripheral.dral
dral/templates/dral/register.dral
dral/templates/mbedAutomatify/__init__.py
dral/templates/mbedAutomatify/field.dral
dral/templates/mbedAutomatify/peripheral.dral
dral/templates/mbedAutomatify/register.dral
dral/templates/mbedAutomatify/register.simple.dral
dral/types.py
dral/utils.py
dral-3.0.0.dist-info/entry_points.txt
dral-3.0.0.dist-info/LICENSE
dral-3.0.0.dist-info/WHEEL
dral-3.0.0.dist-info/METADATA
dral-3.0.0.dist-info/RECORD
