Metadata-Version: 2.1
Name: dral
Version: 3.0.0
Summary: D-RAL - Device Register Access Layer
Home-page: https://github.com/gembcior/d-ral
License: MIT
Author: Gembcior
Author-email: gembcior@gmail.com
Requires-Python: >=3.8,<4.0
Classifier: Environment :: Console
Classifier: License :: OSI Approved :: MIT License
Classifier: Operating System :: POSIX :: Linux
Classifier: Programming Language :: Python :: 3
Classifier: Programming Language :: Python :: 3.8
Classifier: Programming Language :: Python :: 3.9
Classifier: Programming Language :: Python :: 3.10
Classifier: Programming Language :: Python :: 3.10
Classifier: Programming Language :: Python :: 3.8
Classifier: Programming Language :: Python :: 3.9
Requires-Dist: click (>=8.1,<9.0)
Requires-Dist: pylama[all] (>=8.4.1,<9.0.0)
Requires-Dist: rich (>=12.5,<13.0)
Requires-Dist: svd2py (>=0.1,<0.2)
